pigeonsai/__init__.py
pigeonsai/_client.py
pigeonsai/_constants.py
pigeonsai/_exceptions.py
pigeonsai/resources/__init__.py
pigeonsai/resources/anomaly_detector.py
pigeonsai/resources/data_connector.py
pigeonsai/resources/recommender.py
tensorstack-0.0.0.1.dist-info/METADATA
tensorstack-0.0.0.1.dist-info/WHEEL
tensorstack-0.0.0.1.dist-info/top_level.txt
tensorstack-0.0.0.1.dist-info/RECORD
