Metadata-Version: 2.1
Name: tensorstack
Version: 0.0.0.1
Summary: client and SDK
Author: PigeonsAI Inc.
Author-email: info@pigeonsai.com
License: Proprietary License
Classifier: Intended Audience :: Developers
Classifier: Intended Audience :: Information Technology
Requires-Python: >=3.6
Requires-Dist: requests (>=2.28.2)
Requires-Dist: nltk (==3.8.1)
Requires-Dist: faiss-cpu (==1.7.3)
Requires-Dist: openai (==0.27.4)
Requires-Dist: tenacity (==8.2.2)
Requires-Dist: httpx (==0.26.0)
